main.py
fsbuddy-0.1.0.dist-info/METADATA
fsbuddy-0.1.0.dist-info/WHEEL
fsbuddy-0.1.0.dist-info/entry_points.txt
fsbuddy-0.1.0.dist-info/top_level.txt
fsbuddy-0.1.0.dist-info/RECORD
