Metadata-Version: 2.2
Name: fsbuddy
Version: 0.1.0
Requires-Python: >=3.8
Requires-Dist: send2trash>=1.8.0
Dynamic: requires-dist
Dynamic: requires-python
